wagtail_oidc_provider/__init__.py
wagtail_oidc_provider/apps.py
wagtail_oidc_provider/wagtail_hooks.py
wagtail_oidc_provider/templates/wagtailadmin/wagtail_oidc_provider/panels/kid_panel.html
wagtail_oidc_provider-0.1.0.dist-info/licenses/LICENCE
wagtail_oidc_provider-0.1.0.dist-info/METADATA
wagtail_oidc_provider-0.1.0.dist-info/WHEEL
wagtail_oidc_provider-0.1.0.dist-info/top_level.txt
wagtail_oidc_provider-0.1.0.dist-info/RECORD
